nudb_use/.gitignore
nudb_use/CLEANUP.md
nudb_use/__init__.py
nudb_use/exceptions/__init__.py
nudb_use/exceptions/exception_classes.py
nudb_use/exceptions/groups.py
nudb_use/metadata/__init__.py
nudb_use/metadata/external_apis/brreg_api.py
nudb_use/metadata/external_apis/skolereg.py
nudb_use/metadata/nudb_config/__init__.py
nudb_use/metadata/nudb_config/find_var_missing.py
nudb_use/metadata/nudb_config/get_variable_info.py
nudb_use/metadata/nudb_config/map_get_dtypes.py
nudb_use/metadata/nudb_config/set_options.py
nudb_use/metadata/nudb_config/variable_names.py
nudb_use/metadata/nudb_klass/__init__.py
nudb_use/metadata/nudb_klass/codes.py
nudb_use/metadata/nudb_klass/correspondence.py
nudb_use/metadata/nudb_klass/klass_utils.py
nudb_use/metadata/nudb_klass/labels.py
nudb_use/metadata/nudb_klass/variants.py
nudb_use/nudb_logger.py
nudb_use/paths/__init__.py
nudb_use/paths/latest.py
nudb_use/paths/path_parse.py
nudb_use/paths/path_utils.py
nudb_use/quality/IDEAS.md
nudb_use/quality/__init__.py
nudb_use/quality/check_drop_cols.py
nudb_use/quality/colored_views.py
nudb_use/quality/duplicated_columns.py
nudb_use/quality/missing.py
nudb_use/quality/outdated_variables.py
nudb_use/quality/specific_variables/__init__.py
nudb_use/quality/specific_variables/gro_elevstatus.py
nudb_use/quality/specific_variables/grunnskolepoeng.py
nudb_use/quality/specific_variables/kommune.py
nudb_use/quality/specific_variables/land.py
nudb_use/quality/specific_variables/nus2000.py
nudb_use/quality/specific_variables/run_all.py
nudb_use/quality/specific_variables/skoleaar.py
nudb_use/quality/specific_variables/sn07.py
nudb_use/quality/specific_variables/snr_fnr.py
nudb_use/quality/specific_variables/unique_per_person.py
nudb_use/quality/specific_variables/utils.py
nudb_use/quality/specific_variables/vg_fullfoertkode_detaljert.py
nudb_use/quality/suite.py
nudb_use/quality/thresholds.py
nudb_use/quality/values.py
nudb_use/quality/widths.py
nudb_use/utils/packages.py
nudb_use/variables/__init__.py
ssb_nudb_use-2026.1.4.dist-info/METADATA
ssb_nudb_use-2026.1.4.dist-info/WHEEL
ssb_nudb_use-2026.1.4.dist-info/licenses/LICENSE
ssb_nudb_use-2026.1.4.dist-info/RECORD
