Metadata-Version: 2.4
Name: ssb-nudb-use
Version: 2026.1.4
Summary: NUDB Use - is a usage-package for the Norwegian National Education Database cloud-data. Both for data-consumers and data-deliverers
License-Expression: MIT
License-File: LICENSE
Author: Carl F. Corneil
Author-email: cfc@ssb.no
Maintainer: Statistics Norway, Education statistics Department (360)
Requires-Python: >=3.11
Classifier: Development Status :: 3 - Alpha
Classifier: Programming Language :: Python :: 3
Classifier: Programming Language :: Python :: 3.11
Classifier: Programming Language :: Python :: 3.12
Classifier: Programming Language :: Python :: 3.13
Classifier: Programming Language :: Python :: 3.14
Requires-Dist: Jinja2 (>=3.1.0)
Requires-Dist: brreg (>=1.3.0)
Requires-Dist: duckdb (>=1.4.3)
Requires-Dist: pandas (>=2.2.0,<3)
Requires-Dist: pydantic (>=2.12.4)
Requires-Dist: requests (>=2.32.5)
Requires-Dist: ssb-fagfunksjoner (>=1.1.2) ; python_version >= "3.11" and python_version < "4.0"
Requires-Dist: ssb-klass-python (>=1.0.4)
Requires-Dist: ssb-nudb-config (>=2026.1.10)
Project-URL: Changelog, https://github.com/statisticsnorway/ssb-nudb-use/releases
Project-URL: Documentation, https://statisticsnorway.github.io/ssb-nudb-use
Project-URL: Homepage, https://github.com/statisticsnorway/ssb-nudb-use
Project-URL: Repository, https://github.com/statisticsnorway/ssb-nudb-use
